dsu/__init__.py
dsu/analyze.py
dsu/automodel/__init__.py
dsu/automodel/autokeras_cnn.py
dsu/automodel/autokeras_mlp.py
dsu/automodel/autokeras_mnist.py
dsu/automodel/autokeras_obj_det.py
dsu/automodel/autokeras_sent_analy.py
dsu/automodel/autokeras_topics.py
dsu/automodel/autokeras_voice_gen.py
dsu/automodel/autokeras_voice_recog.py
dsu/automodel/requirements.txt
dsu/clusteringModels.py
dsu/datautils.py
dsu/dists.py
dsu/exceptions.py
dsu/explain.py
dsu/features/__init__.py
dsu/features/audio.py
dsu/features/audio_helpers/convert_all.sh
dsu/features/audio_helpers/remove-silence.py
dsu/features/audio_helpers/split-data.py
dsu/features/audio_helpers/wav_format.sh
dsu/features/nlp.py
dsu/features/vision.py
dsu/gapstats.py
dsu/imageProcessingUtils.py
dsu/modelStacking.py
dsu/modelValidators.py
dsu/outliers.py
dsu/plotter.py
dsu/predictiveModels.py
dsu/sampling.py
dsu/settings.py
dsu/sklearnUtils.py
dsu/statsutils.py
dsu/timeSeriesUtils.py
dsu/utils.py
dsu-1.4.0.dist-info/LICENSE.md
dsu-1.4.0.dist-info/WHEEL
dsu-1.4.0.dist-info/METADATA
dsu-1.4.0.dist-info/RECORD
